MANIFEST.in
README.rst
VERSION
requirements.txt
setup.py
feed_to_exporter/__init__.py
feed_to_exporter/__main__.py
feed_to_exporter/exceptions.py
feed_to_exporter/filters.py
feed_to_exporter/helpers.py
feed_to_exporter/model.py
feed_to_exporter/parsers.py
feed_to_exporter/processors.py
feed_to_exporter.egg-info/PKG-INFO
feed_to_exporter.egg-info/SOURCES.txt
feed_to_exporter.egg-info/dependency_links.txt
feed_to_exporter.egg-info/entry_points.txt
feed_to_exporter.egg-info/requires.txt
feed_to_exporter.egg-info/top_level.txt
feed_to_exporter/mongodb/__init__.py
feed_to_exporter/mongodb/cli.py
feed_to_exporter/mongodb/model.py
feed_to_exporter/wordpress/__init__.py
feed_to_exporter/wordpress/cli.py
feed_to_exporter/wordpress/model.py
feed_to_exporter/wordpress/wordpress_queries.py