Metadata-Version: 1.1
Name: feed-to-exporter
Version: 1.0.2
Summary: Export RSS Feed as different outputs: Wordpress, MongoDB
Home-page: https://github.com/cr0hn/feed-to-exporter
Author: cr0hn[-at-]cr0hn.com
Author-email: UNKNOWN
License: BSD 3 License
Platform: UNKNOWN
Classifier: Environment :: Console
Classifier: Intended Audience :: System Administrators
Classifier: Intended Audience :: Other Audience
Classifier: License :: OSI Approved :: BSD License
Classifier: Operating System :: MacOS
Classifier: Operating System :: Microsoft :: Windows
Classifier: Operating System :: POSIX
Classifier: Programming Language :: Python :: 3
